odoo9_addon_mrp_bom_product_details-9.0.1.0.0-py2.7-nspkg.pth
odoo9_addon_mrp_bom_product_details-9.0.1.0.0.dist-info/DESCRIPTION.rst
odoo9_addon_mrp_bom_product_details-9.0.1.0.0.dist-info/METADATA
odoo9_addon_mrp_bom_product_details-9.0.1.0.0.dist-info/RECORD
odoo9_addon_mrp_bom_product_details-9.0.1.0.0.dist-info/WHEEL
odoo9_addon_mrp_bom_product_details-9.0.1.0.0.dist-info/metadata.json
odoo9_addon_mrp_bom_product_details-9.0.1.0.0.dist-info/namespace_packages.txt
odoo9_addon_mrp_bom_product_details-9.0.1.0.0.dist-info/top_level.txt
odoo_addons/mrp_bom_product_details/README.rst
odoo_addons/mrp_bom_product_details/__init__.py
odoo_addons/mrp_bom_product_details/__openerp__.py
odoo_addons/mrp_bom_product_details/i18n/en_US.po
odoo_addons/mrp_bom_product_details/i18n/es.po
odoo_addons/mrp_bom_product_details/models/__init__.py
odoo_addons/mrp_bom_product_details/models/mrp_bom_product_details.py
odoo_addons/mrp_bom_product_details/views/mrp_bom_product_details.xml
